setup.cfg
setup.py
retrykit/__init__.py
retrykit.egg-info/PKG-INFO
retrykit.egg-info/SOURCES.txt
retrykit.egg-info/dependency_links.txt
retrykit.egg-info/top_level.txt