Metadata-Version: 1.0
Name: retrykit
Version: 0.0.2
Summary: The python retry module with context for lazy people.
Home-page: https://github.com/yoshiso/retrykit.git
Author: Sho Yoshida
Author-email: nya060@gmail.com
License: MIT
Platform: UNKNOWN
